plastron/rdfmapping/__init__.py
plastron/rdfmapping/decorators.py
plastron/rdfmapping/descriptors.py
plastron/rdfmapping/embed.py
plastron/rdfmapping/graph.py
plastron/rdfmapping/properties.py
plastron/rdfmapping/resources.py
plastron/rdfmapping/validation.py
plastron_rdf-4.6.2.dist-info/METADATA
plastron_rdf-4.6.2.dist-info/WHEEL
plastron_rdf-4.6.2.dist-info/top_level.txt
plastron_rdf-4.6.2.dist-info/RECORD
